examples/iverilog/rtl/counter.v
module counter(out, clk, reset);

  parameter WIDTH = 8;

  output [WIDTH-1 : 0] out;
  input 	       clk, reset;

  reg [WIDTH-1 : 0]   out;
  wire 	       clk, reset;

  always @(posedge clk)
		if(reset)
				out <= 0;
		else
				out <= out + 1;
endmodule // counter

examples/iverilog/rtl/counter_tb.v
module counter_tb;

  /* Make a reset that pulses once. */
  reg reset = 0;
  initial begin
 $dumpfile("counter_tb.vcd");
 $dumpvars(0,counter_tb);


     # 17 reset = 1;
     # 11 reset = 0;
     # 29 reset = 1;
     # 11 reset = 0;
     # 200 $finish;
  end

  /* Make a regular pulsing clock. */
  reg clk = 0;
  always #5 clk = !clk;

  wire [7:0] value;
  counter c1 (value, clk, reset);

  initial
     $monitor("At time %t, value = %h (%0d)",
              $time, value, value);
endmodule // test

examples/iverilog/counter_tb.vcd
$date
	Sat Apr 27 18:26:21 2019
$end
$version
	Icarus Verilog
$end
$timescale
	1s
$end
$scope module counter_tb $end
$var wire 8 ! value [7:0] $end
$var reg 1 " clk $end
$var reg 1 # reset $end
$scope module c1 $end
$var wire 1 " clk $end
$var wire 1 # reset $end
$var reg 8 $ out [7:0] $end
$upscope $end
$upscope $end
$enddefinitions $end
#0
$dumpvars
bx $
0#
0"
bx !
$end
#5
1"
#10
0"
#15
1"
#17
b0 !
b0 $
1#
#20
0"
#25
1"
#28
0#
#30
0"
#35
b1 !
b1 $
1"
#40
0"
#45
b10 !
b10 $
1"
#50
0"
#55
b11 !
b11 $
1"
#57
b0 !
b0 $
1#
#60
0"
#65
1"
#68
0#
#70
0"
#75
b1 !
b1 $
1"
#80
0"
#85
b10 !
b10 $
1"
#90
0"
#95
b11 !
b11 $
1"
#100
0"
#105
b100 !
b100 $
1"
#110
0"
#115
b101 !
b101 $
1"
#120
0"
#125
b110 !
b110 $
1"
#130
0"
#135
b111 !
b111 $
1"
#140
0"
#145
b1000 !
b1000 $
1"
#150
0"
#155
b1001 !
b1001 $
1"
#160
0"
#165
b1010 !
b1010 $
1"
#170
0"
#175
b1011 !
b1011 $
1"
#180
0"
#185
b1100 !
b1100 $
1"
#190
0"
#195
b1101 !
b1101 $
1"
#200
0"
#205
b1110 !
b1110 $
1"
#210
0"
#215
b1111 !
b1111 $
1"
#220
0"
#225
b10000 !
b10000 $
1"
#230
0"
#235
b10001 !
b10001 $
1"
#240
0"
#245
b10010 !
b10010 $
1"
#250
0"
#255
b10011 !
b10011 $
1"
#260
0"
#265
b10100 !
b10100 $
1"
